memoryscope/__init__.py
memoryscope/constants/__init__.py
memoryscope/constants/common_constants.py
memoryscope/constants/language_constants.py
memoryscope/contrib/example_query_worker.yaml
memoryscope/core/__init__.py
memoryscope/core/memoryscope.py
memoryscope/core/memoryscope_context.py
memoryscope/core/chat/__init__.py
memoryscope/core/chat/api_memory_chat.py
memoryscope/core/chat/base_memory_chat.py
memoryscope/core/chat/cli_memory_chat.py
memoryscope/core/chat/memory_chat_prompt.yaml
memoryscope/core/config/__init__.py
memoryscope/core/config/arguments.py
memoryscope/core/config/config_manager.py
memoryscope/core/config/demo_config.yaml
memoryscope/core/config/demo_config_zh.yaml
memoryscope/core/models/__init__.py
memoryscope/core/models/base_model.py
memoryscope/core/models/dummy_generation_model.py
memoryscope/core/models/llama_index_embedding_model.py
memoryscope/core/models/llama_index_generation_model.py
memoryscope/core/models/llama_index_rank_model.py
memoryscope/core/operation/__init__.py
memoryscope/core/operation/backend_operation.py
memoryscope/core/operation/base_operation.py
memoryscope/core/operation/base_workflow.py
memoryscope/core/operation/consolidate_memory_op.py
memoryscope/core/operation/frontend_operation.py
memoryscope/core/service/__init__.py
memoryscope/core/service/base_memory_service.py
memoryscope/core/service/memory_scope_service.py
memoryscope/core/storage/__init__.py
memoryscope/core/storage/base_memory_store.py
memoryscope/core/storage/base_monitor.py
memoryscope/core/storage/dummy_memory_store.py
memoryscope/core/storage/dummy_monitor.py
memoryscope/core/storage/llama_index_es_memory_store.py
memoryscope/core/storage/llama_index_sync_elasticsearch.py
memoryscope/core/utils/__init__.py
memoryscope/core/utils/datetime_handler.py
memoryscope/core/utils/logger.py
memoryscope/core/utils/prompt_handler.py
memoryscope/core/utils/registry.py
memoryscope/core/utils/response_text_parser.py
memoryscope/core/utils/singleton.py
memoryscope-0.1.1.0.dist-info/LICENSE
memoryscope-0.1.1.0.dist-info/METADATA
memoryscope-0.1.1.0.dist-info/WHEEL
memoryscope-0.1.1.0.dist-info/entry_points.txt
memoryscope-0.1.1.0.dist-info/top_level.txt
memoryscope-0.1.1.0.dist-info/RECORD
