Metadata-Version: 2.1
Name: memoryscope
Version: 0.1.1.0
Summary: MemoryScope is a powerful and flexible long term memory system for LLM chatbots. It consists of a memory database and three customizable system operations, which can be flexibly combined to provide robust long term memory services for your LLM chatbot.
Home-page: https://github.com/modelscope/memoryscope
Author: Li Yu, Tiancheng Qin, Qingxu Fu, Sen Huang, Xianzhe Xu, Zhaoyang Liu, Boyin Liu
Author-email: jinli.yl@alibaba-inc.com, qiancheng.qtc@alibaba-inc.com, fuqingxu.fqx@alibaba-inc.com, huangsen.huang@alibaba-inc.com, xianzhe.xxz@alibaba-inc.com, jingmu.lzy@alibaba-inc.com, liuboyin.lby@alibaba-inc.com
Project-URL: Bug Tracker, https://github.com/modelscope/memoryscope/issues
Classifier: Programming Language :: Python :: 3
Classifier: License :: OSI Approved :: Apache Software License
Classifier: Operating System :: OS Independent
Requires-Python: >=3.10
License-File: LICENSE
Requires-Dist: llama-index ==0.10.45
Requires-Dist: llama-index-embeddings-dashscope >=0.1.3
Requires-Dist: llama-index-llms-dashscope >=0.1.2
Requires-Dist: llama-index-postprocessor-dashscope-rerank-custom >=0.1.0
Requires-Dist: dashscope >=1.19.1
Requires-Dist: llama-index-vector-stores-elasticsearch >=0.2.0
Requires-Dist: elasticsearch >=8.14.0
Requires-Dist: pyfiglet >=1.0.2
Requires-Dist: termcolor >=2.4.0
Requires-Dist: fire >=0.6.0
Requires-Dist: questionary >=2.0.1
Requires-Dist: pydantic >=2.7.1
Requires-Dist: pyyaml >=6.0.1
Requires-Dist: numpy >=1.26.4
Requires-Dist: rich >=13.0.0
